discatcore/__init__.py
discatcore-0.0.0.dist-info/METADATA
discatcore-0.0.0.dist-info/WHEEL
discatcore-0.0.0.dist-info/top_level.txt
discatcore-0.0.0.dist-info/RECORD
